chancepy/BaseRandom.py
chancepy/Basics.py
chancepy/Chance.py
chancepy/TimeChance.py
chancepy/Utils.py
chancepy/__init__.py
chancepy-0.1.4.dist-info/LICENSE
chancepy-0.1.4.dist-info/METADATA
chancepy-0.1.4.dist-info/WHEEL
chancepy-0.1.4.dist-info/RECORD
