Metadata-Version: 2.1
Name: chancepy
Version: 0.1.4
Summary: Random generator helper for Python
Home-page: https://github.com/kovrr/chancepy
Author: Nuni
Author-email: nuni@kovrr.com
Requires-Python: >=3.8,<4.0
Classifier: Programming Language :: Python :: 3
Classifier: Programming Language :: Python :: 3.8
Classifier: Programming Language :: Python :: 3.9
Classifier: Programming Language :: Python :: 3.10
Classifier: Programming Language :: Python :: 3.11
Requires-Dist: pytz (>=2023,<2024)
Project-URL: Repository, https://github.com/kovrr/chancepy
